{
  "totalDelta": 9361,
  "byLou": {
    "029200067A7K6CH0H586": 1,
    "097900BEFH0000000217": 11,
    "98450045AN5EB5FDC780": 8,
    "529900T8BM49AURSDO55": 1534,
    "39120001KULK7200U106": 431,
    "5493001KJTIIGC8Y1R12": 1146,
    "213800WAVVOPS85N2205": 666,
    "635400DZBUIMTBCXGA12": 173,
    "529900F6BNUR3RJ2WH29": 727,
    "506700LOLO7M6V0E4247": 40,
    "52990034RLKT0WSOAM90": 100,
    "815600EAD78C57FCE690": 861,
    "549300O897ZC5H7CY412": 322,
    "378900F4A0A690EA6735": 8,
    "747800R0J5YBJED3N877": 10,
    "5299000J2N45DDNE4Y28": 526,
    "485100001PLJJ09NZT59": 508,
    "253400M18U5TB02TW421": 3,
    "335800FVH4MOKZS9VH40": 291,
    "894500IIP432AHQ64V02": 46,
    "259400L3KBYEVNHEJF55": 137,
    "655600IJ8LS3CCDA4421": 21,
    "315700LK78Z7C0WMIL03": 63,
    "48510000JZ17NWGUA510": 8,
    "353800279ADEFGKNTV65": 75,
    "4469000001AVO26P9X86": 14,
    "959800R2X69K6Y6MX775": 532,
    "254900LXHEVKYGERER05": 13,
    "969500Q2MA9VBQ8BG884": 582,
    "558600FNC30A8J9EGQ54": 11,
    "724500A93Z8V1MJK5349": 305,
    "743700OO8O2N3TQKJC81": 164,
    "789000TVSB96MCOKSB52": 20,
    "984500ID493BDCR4B368": 1,
    "9884008RRMX1X5HV6625": 3
  },
  "byCountry": {
    "NG": 1,
    "SK": 16,
    "DK": 202,
    "US": 741,
    "AU": 251,
    "GB": 543,
    "GR": 145,
    "VG": 40,
    "IE": 147,
    "LU": 187,
    "FR": 693,
    "GG": 23,
    "BE": 138,
    "KY": 92,
    "JE": 31,
    "CY": 30,
    "PT": 45,
    "CH": 130,
    "NZ": 20,
    "VE": 1,
    "EE": 78,
    "MH": 6,
    "HK": 53,
    "DE": 704,
    "KN": 1,
    "SG": 44,
    "LV": 20,
    "VC": 2,
    "HU": 65,
    "IM": 3,
    "BM": 6,
    "IT": 1009,
    "LR": 1,
    "CW": 2,
    "MT": 11,
    "NL": 380,
    "IL": 4,
    "MY": 73,
    "NO": 151,
    "PA": 5,
    "SC": 4,
    "LT": 22,
    "AE": 21,
    "BB": 1,
    "ZA": 13,
    "ES": 614,
    "OM": 1,
    "HR": 10,
    "RO": 25,
    "AL": 1,
    "KW": 2,
    "RU": 2,
    "AM": 1,
    "IN": 1352,
    "CA": 111,
    "BG": 15,
    "MX": 19,
    "SE": 267,
    "MU": 14,
    "TW": 4,
    "SI": 10,
    "IS": 21,
    "BJ": 1,
    "AD": 1,
    "TH": 5,
    "MC": 1,
    "VN": 2,
    "CZ": 73,
    "MO": 1,
    "DO": 1,
    "JP": 76,
    "GI": 2,
    "SA": 11,
    "AR": 4,
    "ID": 3,
    "PL": 148,
    "CN": 21,
    "LI": 35,
    "AT": 128,
    "FI": 179,
    "BR": 8,
    "BD": 1,
    "TR": 25,
    "AO": 1,
    "EU": 1,
    "PK": 1,
    "BS": 2,
    "PE": 1,
    "JO": 1,
    "RS": 1,
    "KR": 3
  },
  "byLouByCountry": {
    "029200067A7K6CH0H586": {
      "NG": 1
    },
    "097900BEFH0000000217": {
      "SK": 11
    },
    "98450045AN5EB5FDC780": {
      "DK": 7,
      "NO": 1
    },
    "529900T8BM49AURSDO55": {
      "DK": 94,
      "AU": 124,
      "GB": 130,
      "VE": 1,
      "HU": 24,
      "MY": 1,
      "BB": 1,
      "LU": 15,
      "IN": 466,
      "LV": 8,
      "BE": 23,
      "NO": 24,
      "MU": 9,
      "EE": 40,
      "US": 51,
      "SG": 18,
      "CZ": 3,
      "DE": 100,
      "ZA": 3,
      "CH": 10,
      "AT": 26,
      "LT": 14,
      "PT": 14,
      "CA": 20,
      "SE": 69,
      "IS": 2,
      "AE": 14,
      "SC": 2,
      "IE": 15,
      "NL": 24,
      "GG": 2,
      "KY": 16,
      "MT": 3,
      "IT": 52,
      "FR": 14,
      "FI": 4,
      "ES": 22,
      "PK": 1,
      "HK": 13,
      "CY": 11,
      "JE": 3,
      "IM": 1,
      "BR": 5,
      "RO": 7,
      "CN": 3,
      "VG": 3,
      "MH": 2,
      "BS": 2,
      "BG": 5,
      "PL": 5,
      "AR": 1,
      "TR": 4,
      "PE": 1,
      "GI": 1,
      "JO": 1,
      "GR": 3,
      "PA": 1,
      "NZ": 2,
      "RS": 1
    },
    "39120001KULK7200U106": {
      "US": 9,
      "LU": 36,
      "VG": 3,
      "DE": 303,
      "LI": 2,
      "AT": 12,
      "AE": 1,
      "CH": 47,
      "IT": 1,
      "GB": 3,
      "MX": 1,
      "KY": 8,
      "IE": 1,
      "HK": 1,
      "GG": 1,
      "SK": 1,
      "IN": 1
    },
    "5493001KJTIIGC8Y1R12": {
      "US": 643,
      "LU": 15,
      "JE": 15,
      "GG": 4,
      "GB": 39,
      "KY": 47,
      "PA": 2,
      "VG": 19,
      "IN": 9,
      "MY": 72,
      "ZA": 1,
      "AU": 50,
      "NL": 6,
      "CA": 41,
      "BG": 1,
      "MX": 3,
      "ES": 7,
      "NO": 11,
      "BE": 11,
      "DE": 11,
      "HK": 7,
      "FR": 3,
      "SG": 17,
      "SE": 11,
      "DK": 3,
      "CY": 7,
      "TW": 3,
      "NZ": 12,
      "MT": 3,
      "CH": 4,
      "SI": 3,
      "MU": 3,
      "AE": 4,
      "IS": 4,
      "EE": 8,
      "IE": 11,
      "IL": 3,
      "BJ": 1,
      "AD": 1,
      "TH": 3,
      "HU": 3,
      "MC": 1,
      "BM": 4,
      "VN": 1,
      "CZ": 1,
      "MO": 1,
      "RO": 1,
      "SC": 1,
      "DO": 1,
      "PT": 4,
      "IT": 2,
      "JP": 1,
      "GI": 1,
      "SA": 1,
      "AR": 1,
      "ID": 1,
      "MH": 1,
      "BR": 1,
      "CN": 1
    },
    "213800WAVVOPS85N2205": {
      "GB": 304,
      "VG": 9,
      "IE": 60,
      "FR": 11,
      "GG": 16,
      "US": 14,
      "BE": 6,
      "KY": 15,
      "JE": 13,
      "CY": 3,
      "LU": 51,
      "PT": 9,
      "CH": 15,
      "NZ": 5,
      "GR": 32,
      "EE": 3,
      "AU": 7,
      "MH": 3,
      "HK": 16,
      "DE": 11,
      "KN": 1,
      "SG": 4,
      "LV": 1,
      "IM": 2,
      "BM": 2,
      "LR": 1,
      "CW": 1,
      "MT": 3,
      "NL": 8,
      "IL": 1,
      "DK": 3,
      "NO": 1,
      "SC": 1,
      "LT": 2,
      "AE": 1,
      "OM": 1,
      "RO": 3,
      "AL": 1,
      "KW": 2,
      "MU": 2,
      "IN": 2,
      "VN": 1,
      "ZA": 1,
      "IT": 7,
      "ES": 1,
      "CZ": 1,
      "PL": 2,
      "BD": 1,
      "TW": 1,
      "TR": 2,
      "TH": 2,
      "SE": 1
    },
    "635400DZBUIMTBCXGA12": {
      "GR": 110,
      "IE": 51,
      "KY": 3,
      "GB": 4,
      "NO": 1,
      "BG": 1,
      "LU": 2,
      "NL": 1
    },
    "529900F6BNUR3RJ2WH29": {
      "GB": 21,
      "VC": 1,
      "DK": 30,
      "LU": 17,
      "ES": 26,
      "HU": 10,
      "IN": 247,
      "SE": 27,
      "CH": 7,
      "BE": 15,
      "PT": 14,
      "IE": 6,
      "NO": 24,
      "CZ": 5,
      "DE": 37,
      "LV": 3,
      "AT": 3,
      "US": 7,
      "CA": 49,
      "CY": 3,
      "NL": 21,
      "AU": 18,
      "FR": 79,
      "IT": 41,
      "EE": 4,
      "FI": 5,
      "BG": 2,
      "KY": 2,
      "BR": 1,
      "ID": 1,
      "VG": 1
    },
    "506700LOLO7M6V0E4247": {
      "CH": 39,
      "LI": 1
    },
    "52990034RLKT0WSOAM90": {
      "HK": 15,
      "HU": 22,
      "AT": 3,
      "SG": 4,
      "BR": 1,
      "NL": 1,
      "BE": 10,
      "LU": 2,
      "GB": 3,
      "DE": 22,
      "AU": 8,
      "NO": 1,
      "PT": 1,
      "LI": 2,
      "US": 1,
      "VC": 1,
      "ES": 1,
      "DK": 1,
      "AO": 1
    },
    "815600EAD78C57FCE690": {
      "IT": 860,
      "LU": 1
    },
    "549300O897ZC5H7CY412": {
      "LU": 28,
      "CY": 1,
      "GB": 5,
      "NO": 80,
      "PL": 1,
      "SE": 141,
      "IS": 12,
      "FI": 5,
      "DK": 31,
      "US": 4,
      "SK": 1,
      "IN": 6,
      "VG": 1,
      "IE": 1,
      "AU": 2,
      "NL": 1,
      "CZ": 1,
      "LI": 1
    },
    "378900F4A0A690EA6735": {
      "ZA": 8
    },
    "747800R0J5YBJED3N877": {
      "HR": 10
    },
    "5299000J2N45DDNE4Y28": {
      "ES": 25,
      "LU": 18,
      "CH": 8,
      "PL": 3,
      "NL": 1,
      "DE": 219,
      "AT": 83,
      "DK": 2,
      "IT": 45,
      "US": 11,
      "CZ": 1,
      "PA": 2,
      "LI": 29,
      "MX": 1,
      "SE": 2,
      "CY": 5,
      "VG": 2,
      "PT": 3,
      "IE": 2,
      "FR": 3,
      "AU": 42,
      "EE": 1,
      "GB": 4,
      "AR": 2,
      "BG": 2,
      "NZ": 1,
      "BE": 3,
      "HU": 1,
      "SK": 1,
      "SG": 1,
      "NO": 1,
      "CA": 1,
      "CW": 1
    },
    "485100001PLJJ09NZT59": {
      "GB": 30,
      "SE": 16,
      "IN": 330,
      "BG": 4,
      "AT": 1,
      "DK": 31,
      "NO": 7,
      "NL": 11,
      "BE": 24,
      "FI": 1,
      "EE": 21,
      "HU": 5,
      "LT": 6,
      "LV": 8,
      "PL": 4,
      "IS": 3,
      "FR": 2,
      "LU": 2,
      "US": 1,
      "CZ": 1
    },
    "253400M18U5TB02TW421": {
      "RU": 2,
      "AM": 1
    },
    "335800FVH4MOKZS9VH40": {
      "IN": 291
    },
    "894500IIP432AHQ64V02": {
      "BE": 46
    },
    "259400L3KBYEVNHEJF55": {
      "PL": 133,
      "IT": 1,
      "DE": 1,
      "EE": 1,
      "RO": 1
    },
    "655600IJ8LS3CCDA4421": {
      "VG": 2,
      "CN": 17,
      "KY": 1,
      "HK": 1
    },
    "315700LK78Z7C0WMIL03": {
      "CZ": 60,
      "SK": 2,
      "SI": 1
    },
    "48510000JZ17NWGUA510": {
      "SI": 6,
      "MT": 2
    },
    "353800279ADEFGKNTV65": {
      "JP": 75
    },
    "4469000001AVO26P9X86": {
      "MX": 14
    },
    "959800R2X69K6Y6MX775": {
      "ES": 532
    },
    "254900LXHEVKYGERER05": {
      "RO": 13
    },
    "969500Q2MA9VBQ8BG884": {
      "FR": 581,
      "EU": 1
    },
    "558600FNC30A8J9EGQ54": {
      "SA": 10,
      "AE": 1
    },
    "724500A93Z8V1MJK5349": {
      "NL": 305
    },
    "743700OO8O2N3TQKJC81": {
      "FI": 164
    },
    "789000TVSB96MCOKSB52": {
      "TR": 19,
      "NL": 1
    },
    "984500ID493BDCR4B368": {
      "ID": 1
    },
    "9884008RRMX1X5HV6625": {
      "KR": 3
    }
  },
  "byLouStatus": {
    "029200067A7K6CH0H586": {
      "ISSUED": 1
    },
    "097900BEFH0000000217": {
      "ISSUED": 9,
      "LAPSED": 2
    },
    "98450045AN5EB5FDC780": {
      "PENDING_TRANSFER": 1,
      "ISSUED": 5,
      "LAPSED": 2
    },
    "529900T8BM49AURSDO55": {
      "ISSUED": 1225,
      "RETIRED": 54,
      "LAPSED": 196,
      "PENDING_TRANSFER": 46,
      "PENDING_ARCHIVAL": 13
    },
    "39120001KULK7200U106": {
      "ISSUED": 405,
      "PENDING_ARCHIVAL": 5,
      "RETIRED": 12,
      "LAPSED": 6,
      "PENDING_TRANSFER": 3
    },
    "5493001KJTIIGC8Y1R12": {
      "ISSUED": 968,
      "RETIRED": 68,
      "LAPSED": 99,
      "PENDING_TRANSFER": 8,
      "PENDING_ARCHIVAL": 3
    },
    "213800WAVVOPS85N2205": {
      "ISSUED": 544,
      "PENDING_TRANSFER": 31,
      "LAPSED": 51,
      "RETIRED": 26,
      "PENDING_ARCHIVAL": 14
    },
    "635400DZBUIMTBCXGA12": {
      "ISSUED": 154,
      "LAPSED": 5,
      "PENDING_TRANSFER": 3,
      "RETIRED": 10,
      "PENDING_ARCHIVAL": 1
    },
    "529900F6BNUR3RJ2WH29": {
      "ISSUED": 522,
      "PENDING_ARCHIVAL": 15,
      "LAPSED": 171,
      "PENDING_TRANSFER": 17,
      "RETIRED": 2
    },
    "506700LOLO7M6V0E4247": {
      "ISSUED": 33,
      "LAPSED": 6,
      "RETIRED": 1
    },
    "52990034RLKT0WSOAM90": {
      "ISSUED": 78,
      "PENDING_TRANSFER": 5,
      "LAPSED": 9,
      "RETIRED": 8
    },
    "815600EAD78C57FCE690": {
      "ISSUED": 763,
      "LAPSED": 88,
      "RETIRED": 7,
      "PENDING_ARCHIVAL": 1,
      "PENDING_TRANSFER": 2
    },
    "549300O897ZC5H7CY412": {
      "ISSUED": 256,
      "LAPSED": 48,
      "RETIRED": 5,
      "PENDING_ARCHIVAL": 2,
      "PENDING_TRANSFER": 10,
      "ANNULLED": 1
    },
    "378900F4A0A690EA6735": {
      "LAPSED": 6,
      "ISSUED": 2
    },
    "747800R0J5YBJED3N877": {
      "ISSUED": 7,
      "LAPSED": 3
    },
    "5299000J2N45DDNE4Y28": {
      "ISSUED": 390,
      "PENDING_ARCHIVAL": 4,
      "LAPSED": 62,
      "RETIRED": 61,
      "PENDING_TRANSFER": 9
    },
    "485100001PLJJ09NZT59": {
      "ISSUED": 443,
      "LAPSED": 59,
      "PENDING_TRANSFER": 4,
      "PENDING_ARCHIVAL": 2
    },
    "253400M18U5TB02TW421": {
      "ISSUED": 2,
      "RETIRED": 1
    },
    "335800FVH4MOKZS9VH40": {
      "ISSUED": 236,
      "LAPSED": 16,
      "PENDING_TRANSFER": 23,
      "PENDING_ARCHIVAL": 16
    },
    "894500IIP432AHQ64V02": {
      "ISSUED": 41,
      "PENDING_TRANSFER": 2,
      "LAPSED": 3
    },
    "259400L3KBYEVNHEJF55": {
      "ISSUED": 124,
      "RETIRED": 2,
      "LAPSED": 10,
      "PENDING_ARCHIVAL": 1
    },
    "655600IJ8LS3CCDA4421": {
      "ISSUED": 14,
      "LAPSED": 7
    },
    "315700LK78Z7C0WMIL03": {
      "ISSUED": 46,
      "LAPSED": 17
    },
    "48510000JZ17NWGUA510": {
      "ISSUED": 7,
      "LAPSED": 1
    },
    "353800279ADEFGKNTV65": {
      "ISSUED": 74,
      "LAPSED": 1
    },
    "4469000001AVO26P9X86": {
      "ISSUED": 13,
      "LAPSED": 1
    },
    "959800R2X69K6Y6MX775": {
      "ISSUED": 446,
      "LAPSED": 55,
      "RETIRED": 16,
      "PENDING_ARCHIVAL": 5,
      "PENDING_TRANSFER": 10
    },
    "254900LXHEVKYGERER05": {
      "ISSUED": 12,
      "PENDING_TRANSFER": 1
    },
    "969500Q2MA9VBQ8BG884": {
      "LAPSED": 128,
      "ISSUED": 446,
      "RETIRED": 8
    },
    "558600FNC30A8J9EGQ54": {
      "ISSUED": 7,
      "LAPSED": 4
    },
    "724500A93Z8V1MJK5349": {
      "ISSUED": 273,
      "LAPSED": 19,
      "DUPLICATE": 1,
      "RETIRED": 5,
      "PENDING_TRANSFER": 6,
      "PENDING_ARCHIVAL": 1
    },
    "743700OO8O2N3TQKJC81": {
      "ISSUED": 145,
      "RETIRED": 6,
      "LAPSED": 13
    },
    "789000TVSB96MCOKSB52": {
      "ISSUED": 20
    },
    "984500ID493BDCR4B368": {
      "ISSUED": 1
    },
    "9884008RRMX1X5HV6625": {
      "ISSUED": 3
    }
  },
  "statusBreakdown": {
    "ISSUED": 7715,
    "LAPSED": 1088,
    "PENDING_TRANSFER": 181,
    "RETIRED": 292,
    "PENDING_ARCHIVAL": 83,
    "ANNULLED": 1,
    "DUPLICATE": 1
  },
  "transfers": {
    "outflows": {
      "98450045AN5EB5FDC780": 1,
      "213800WAVVOPS85N2205": 31,
      "635400DZBUIMTBCXGA12": 3,
      "529900T8BM49AURSDO55": 46,
      "52990034RLKT0WSOAM90": 5,
      "5493001KJTIIGC8Y1R12": 8,
      "335800FVH4MOKZS9VH40": 23,
      "529900F6BNUR3RJ2WH29": 17,
      "39120001KULK7200U106": 3,
      "5299000J2N45DDNE4Y28": 9,
      "549300O897ZC5H7CY412": 10,
      "894500IIP432AHQ64V02": 2,
      "485100001PLJJ09NZT59": 4,
      "724500A93Z8V1MJK5349": 6,
      "254900LXHEVKYGERER05": 1,
      "815600EAD78C57FCE690": 2,
      "959800R2X69K6Y6MX775": 10
    },
    "inflows": {}
  },
  "date": "2026-07-15"
}